{
  "$schema": "https://schema.management.azure.com/schemas/2019-04-01/deploymentParameters.json#",
  "contentVersion": "1.0.0.0",
  "parameters": {
    "location": {
      "value": "centralindia"
    },
    "storageAccountName": {
      "value": "stprivatedev300"
    },
    "vnetName":{
      "value": "vnetprivatedev300"
    },
    "addressPrefix":{
      "value": "10.1.0.0/16"
    },
    "subnetAddressPrefix": {
      "value" : "10.1.0.0/24"
    },
    "subnetName1": {
      "value" : "subnet-2"
    },
    "nicName":{
      "value": "nicprivatedev300"
    }
  }
}